Workbook

Sheet Product Profitability
A1: Q1 2026 Product Profitability Analysis — SaaS Co.
A2: Contribution margin by product line | All figures in $ thousands
A4: Product | B4: Revenue | C4: COGS | D4: Gross Profit | E4: GM % | F4: OpEx Allocated | G4: Contribution Margin | H4: CM % | I4: Recommendation
A5: Core Platform | B5: 13200 | C5: 2640 | D5: =B5-C5 -> 10560 | E5: =IFERROR(D5/B5,0) -> 0.8 | F5: 6400 | G5: =D5-F5 -> 4160 | H5: =IFERROR(G5/B5,0) -> 0.31515152 | I5: Invest
A6: Analytics Add-on | B6: 5400 | C6: 540 | D6: =B6-C6 -> 4860 | E6: =IFERROR(D6/B6,0) -> 0.9 | F6: 1350 | G6: =D6-F6 -> 3510 | H6: =IFERROR(G6/B6,0) -> 0.65 | I6: Double Down
A7: Professional Services | B7: 2500 | C7: 1750 | D7: =B7-C7 -> 750 | E7: =IFERROR(D7/B7,0) -> 0.3 | F7: 620 | G7: =D7-F7 -> 130 | H7: =IFERROR(G7/B7,0) -> 0.052 | I7: Restructure Pricing
A8: Enterprise Tier | B8: 4200 | C8: 1260 | D8: =B8-C8 -> 2940 | E8: =IFERROR(D8/B8,0) -> 0.7 | F8: 2300 | G8: =D8-F8 -> 640 | H8: =IFERROR(G8/B8,0) -> 0.15238095 | I8: Review Support Model
A9: Legacy Module | B9: 1100 | C9: 385 | D9: =B9-C9 -> 715 | E9: =IFERROR(D9/B9,0) -> 0.65 | F9: 1100 | G9: =D9-F9 -> -385 | H9: =IFERROR(G9/B9,0) -> -0.35 | I9: Sunset
A10: Total | B10: =SUM(B5:B9) -> 26400 | C10: =SUM(C5:C9) -> 6575 | D10: =SUM(D5:D9) -> 19825 | E10: =IFERROR(D10/B10,0) -> 0.75094697 | F10: =SUM(F5:F9) -> 11770 | G10: =SUM(G5:G9) -> 8055 | H10: =IFERROR(G10/B10,0) -> 0.30511364
A13: Headline Finding
A14: Two products (Core Platform and Analytics Add-on) generate 95% of contribution margin. Legacy Module is operating at a loss.

Sheet Revenue Trend
A1: Quarterly Revenue Trend by Product
A2: Last 5 quarters | All figures in $ thousands
A4: Product | B4: Q1 2025 | C4: Q2 2025 | D4: Q3 2025 | E4: Q4 2025 | F4: Q1 2026 | G4: 5Q Growth % | H4: Trajectory
A5: Core Platform | B5: 11500 | C5: 12000 | D5: 12500 | E5: 13000 | F5: 13200 | G5: =IFERROR((F5-B5)/B5,0) -> 0.14782609 | H5: Steady
A6: Analytics Add-on | B6: 3200 | C6: 3800 | D6: 4400 | E6: 5000 | F6: 5400 | G6: =IFERROR((F6-B6)/B6,0) -> 0.6875 | H6: Accelerating
A7: Professional Services | B7: 2800 | C7: 2700 | D7: 2600 | E7: 2500 | F7: 2500 | G7: =IFERROR((F7-B7)/B7,0) -> -0.10714286 | H7: Flat to Down
A8: Enterprise Tier | B8: 3500 | C8: 3800 | D8: 4000 | E8: 4100 | F8: 4200 | G8: =IFERROR((F8-B8)/B8,0) -> 0.2 | H8: Steady
A9: Legacy Module | B9: 1800 | C9: 1600 | D9: 1400 | E9: 1200 | F9: 1100 | G9: =IFERROR((F9-B9)/B9,0) -> -0.38888889 | H9: Declining
A10: Total Revenue | B10: =SUM(B5:B9) -> 22800 | C10: =SUM(C5:C9) -> 23900 | D10: =SUM(D5:D9) -> 24900 | E10: =SUM(E5:E9) -> 25800 | F10: =SUM(F5:F9) -> 26400 | G10: =IFERROR((F10-B10)/B10,0) -> 0.15789474

Sheet Cost Allocation
A1: Q1 2026 OpEx Allocation by Product
A2: Operating costs allocated to each product line | All figures in $ thousands
A4: Product | B4: Sales & Marketing | C4: Customer Success | D4: R&D / Maintenance | E4: G&A Allocation | F4: Total OpEx | G4: % of Revenue
A5: Core Platform | B5: 3200 | C5: 800 | D5: 2000 | E5: 400 | F5: =SUM(B5:E5) -> 6400 | G5: =IFERROR(F5/'Product Profitability'!B5,0) -> 0.48484848
A6: Analytics Add-on | B6: 400 | C6: 200 | D6: 600 | E6: 150 | F6: =SUM(B6:E6) -> 1350 | G6: =IFERROR(F6/'Product Profitability'!B6,0) -> 0.25
A7: Professional Services | B7: 200 | C7: 300 | D7: 50 | E7: 70 | F7: =SUM(B7:E7) -> 620 | G7: =IFERROR(F7/'Product Profitability'!B7,0) -> 0.248
A8: Enterprise Tier | B8: 1100 | C8: 900 | D8: 200 | E8: 100 | F8: =SUM(B8:E8) -> 2300 | G8: =IFERROR(F8/'Product Profitability'!B8,0) -> 0.54761905
A9: Legacy Module | B9: 50 | C9: 500 | D9: 500 | E9: 50 | F9: =SUM(B9:E9) -> 1100 | G9: =IFERROR(F9/'Product Profitability'!B9,0) -> 1
A10: Total | B10: =SUM(B5:B9) -> 4950 | C10: =SUM(C5:C9) -> 2700 | D10: =SUM(D5:D9) -> 3350 | E10: =SUM(E5:E9) -> 770 | F10: =SUM(F5:F9) -> 11770 | G10: =IFERROR(F10/'Product Profitability'!B10,0) -> 0.44583333

Sheet Customer Metrics
A1: Q1 2026 Customer Metrics by Product
A2: Customer counts, concentration, and economics by product line
A4: Product | B4: Customer Count | C4: Top 10 % of Revenue | D4: Avg Revenue per Customer ($) | E4: Cost to Serve per Customer ($) | F4: Quarterly Churn % | G4: Concentration Risk
A5: Core Platform | B5: 850 | C5: 0.18 | D5: =IFERROR('Product Profitability'!B5*1000/B5,0) -> 15529.412 | E5: =IFERROR('Cost Allocation'!C5*1000/B5,0) -> 941.17647 | F5: 0.02 | G5: Low
A6: Analytics Add-on | B6: 420 | C6: 0.15 | D6: =IFERROR('Product Profitability'!B6*1000/B6,0) -> 12857.143 | E6: =IFERROR('Cost Allocation'!C6*1000/B6,0) -> 476.19048 | F6: 0.012 | G6: Low
A7: Professional Services | B7: 95 | C7: 0.35 | D7: =IFERROR('Product Profitability'!B7*1000/B7,0) -> 26315.789 | E7: =IFERROR('Cost Allocation'!C7*1000/B7,0) -> 3157.8947 | F7: 0.08 | G7: Medium
A8: Enterprise Tier | B8: 28 | C8: 0.62 | D8: =IFERROR('Product Profitability'!B8*1000/B8,0) -> 150000 | E8: =IFERROR('Cost Allocation'!C8*1000/B8,0) -> 32142.857 | F8: 0.005 | G8: High
A9: Legacy Module | B9: 180 | C9: 0.22 | D9: =IFERROR('Product Profitability'!B9*1000/B9,0) -> 6111.1111 | E9: =IFERROR('Cost Allocation'!C9*1000/B9,0) -> 2777.7778 | F9: 0.12 | G9: Sunset
A10: Total / Average | B10: =SUM(B5:B9) -> 1573 | C10: =IFERROR(SUMPRODUCT(C5:C9,'Product Profitability'!B5:B9)/SUM('Product Profitability'!B5:B9),0) -> 0.26162879 | D10: =IFERROR('Product Profitability'!B10*1000/B10,0) -> 16783.217 | E10: =IFERROR('Cost Allocation'!C10*1000/B10,0) -> 1716.4654 | F10: =IFERROR(SUMPRODUCT(F5:F9,B5:B9)/B10,0) -> 0.0326637

Sheet Commentary
A1: Q1 2026 Product Strategy Recommendations
A2: Per-product analysis and recommended action for the leadership team
A4: Product | B4: Recommendation | C4: Rationale | D4: Decision Required
A5: Core Platform | B5: Invest | C5: Anchor product. Steady 15% growth across the last 5 quarters with healthy 31.5% contribution margin. Generates the largest absolute profit dollars. Continued investment in platform capabilities is justified by both market position and unit economics. | D5: Approve $2M incremental R&D investment in H2 to maintain feature velocity
A6: Analytics Add-on | B6: Double Down | C6: Highest contribution margin in the portfolio at 65.0%. Generates 44% of total contribution on just 20% of revenue. Revenue growing at 69% over 5 quarters. The most underweighted opportunity in the portfolio. | D6: Pull forward Q3 advanced tier launch to Q2. Add 3 dedicated AEs and 1 PMM
A7: Professional Services | B7: Restructure Pricing | C7: Contribution margin compressed to 5.2% due to high direct delivery costs (70% COGS) and elevated customer success allocation. Either the product is mispriced or it should be repositioned as a strategic enabler subsidized by Core Platform revenue. | D7: CFO and CRO to align on pricing model by end of Q2. Two viable options on the table
A8: Enterprise Tier | B8: Review Support Model | C8: Top 5 customers represent 62% of revenue, creating concentration risk. Cost to serve is $32K per customer per quarter, driven by white-glove support that may not be sustainable at scale. Margin is acceptable at 15.2% but compressed relative to peer SaaS benchmarks. | D8: Customer Success leadership to propose tiered support model with self-service for routine issues by Q2 end
A9: Legacy Module | B9: Sunset | C9: Negative contribution margin of -35.0%. Maintenance and support costs ($1.0M) exceed gross profit ($715K). Revenue declining 39% over 5 quarters with 12% quarterly churn. Continued operation is dilutive to overall profitability and consumes engineering capacity that should be redirected to Analytics. | D9: Approve 12-month sunset plan. Migrate remaining 180 customers to Core Platform with incentive package
